{
    "homepage": "https://github.com/JTNDev/galaxy-integration-wii",
    "version": "0.2.0",
    "url": "https://github.com/JTNDev/galaxy-integration-wii/releases/download/v0.2.0/Dolphin.Wii.Plugin.v0.2.zip",
    "hash": "0e0eb624b515e186e5e262403c439e8d9f51649f8840b1812208990346757512",
    "extract_dir": "dolphin_fc3e85e4-c66b-4310-96c0-8f95cc43e546",
    "extract_to": "integration",
    "pre_install": [
        "if (!(Test-Path \"$persist_dir\\integration\\user_config.py\")) {",
        "    New-Item \"$dir\\integration\\user_config.py\" -Type File | Out-Null",
        "}"
    ],
    "persist": "integration\\user_config.py",
    "checkver": {
        "github": "https://github.com/JTNDev/galaxy-integration-wii",
        "re": "/releases/download/v([\\d.]+)/(?<file>(galaxy-integration-wii(-)?|Wii.Dolphin.|Dolphin.Wii.Plugin.)(v)?([\\d.]+)?.(zip|7z))"
    },
    "autoupdate": {
        "url": "https://github.com/JTNDev/galaxy-integration-wii/releases/download/v$version/$matchFile"
    }
}
